okta_python
