Metadata-Version: 1.1
Name: okta-python
Version: 0.1.0
Summary: Collection of Okta Modules for Okta Api
Home-page: UNKNOWN
Author: Sunny Shahi
Author-email: shahisunny.990@gmail.com
License: MIT
Keywords: Okta,api
Platform: UNKNOWN
Classifier: Development Status :: 5 - Production/Stable
Classifier: Intended Audience :: Education
Classifier: License :: OSI Approved :: MIT License
Classifier: Programming Language :: Python :: 3.8
